pypgtable/__init__.py
pypgtable/base_validator.py
pypgtable/common.py
pypgtable/database.py
pypgtable/pypgtable_typing.py
pypgtable/raw_table.py
pypgtable/row_iterators.py
pypgtable/table.py
pypgtable/validators.py
pypgtable-0.0.1.dev12.dist-info/LICENSE
pypgtable-0.0.1.dev12.dist-info/METADATA
pypgtable-0.0.1.dev12.dist-info/WHEEL
pypgtable-0.0.1.dev12.dist-info/top_level.txt
pypgtable-0.0.1.dev12.dist-info/RECORD
