Metadata-Version: 2.1
Name: pypgtable
Version: 0.0.1.dev12
Summary: A quick & easy way to manage postgresql tables.
Author: Shaped Sundew
Project-URL: Homepage, https://github.com/Shapedsundew9/pypgtable
Project-URL: Bug Tracker, https://github.com/Shapedsundew9/pypgtable/issues
Classifier: Programming Language :: Python :: 3.11
Classifier: License :: OSI Approved :: MIT License
Classifier: Operating System :: OS Independent
Classifier: Development Status :: 2 - Pre-Alpha
Requires-Python: >=3.11
License-File: LICENSE
